ntyp/__init__.py
ntyp/_modidx.py
ntyp/_tmp.py
ntyp/core.py
ntyp-0.0.2.dist-info/LICENSE
ntyp-0.0.2.dist-info/METADATA
ntyp-0.0.2.dist-info/WHEEL
ntyp-0.0.2.dist-info/entry_points.txt
ntyp-0.0.2.dist-info/top_level.txt
ntyp-0.0.2.dist-info/RECORD
