Metadata-Version: 2.1
Name: ntyp
Version: 0.0.2
Summary: ntyp (type alias)
Home-page: https://github.com/dsm-72/ntyp
Author: dsm-72
Author-email: sumner.magruder@yale.edu
License: Apache Software License 2.0
Keywords: nbdev jupyter notebook python types type alias type ntyp typ optional opt
Classifier: Development Status :: 4 - Beta
Classifier: Intended Audience :: Developers
Classifier: Natural Language :: English
Classifier: Programming Language :: Python :: 3.11
Classifier: License :: OSI Approved :: Apache Software License
Requires-Python: >=3.11
License-File: LICENSE
Provides-Extra: dev
